nstimes/__init__.py
nstimes/departure.py
nstimes/main.py
nstimes/printers.py
nstimes/stations.json
nstimes/styles.py
nstimes/utils.py
nstimes-0.4.8.dist-info/METADATA
nstimes-0.4.8.dist-info/WHEEL
nstimes-0.4.8.dist-info/entry_points.txt
nstimes-0.4.8.dist-info/RECORD
