Metadata-Version: 2.1
Name: nstimes
Version: 0.4.8
Summary: CLI tool to obtain schedule info from the dutch railway services
Home-page: https://github.com/evanraalte/nstimes
License: MIT
Keywords: nederland,NS,spoorwegen,Nederlandse,reisplanner
Author: Erik van Raalte
Requires-Python: >=3.10,<4.0
Classifier: License :: OSI Approved :: MIT License
Classifier: Programming Language :: Python :: 3
Classifier: Programming Language :: Python :: 3.10
Classifier: Programming Language :: Python :: 3.11
Classifier: Programming Language :: Python :: 3.12
Requires-Dist: httpx (>=0.25.0,<0.26.0)
Requires-Dist: pydantic (>=2.4.2,<3.0.0)
Requires-Dist: pydantic-settings (>=2.0.3,<3.0.0)
Requires-Dist: python-dotenv (>=1.0.0,<2.0.0)
Requires-Dist: typer[all] (>=0.9.0,<0.10.0)
Project-URL: Repository, https://github.com/evanraalte/nstimes
